README.md
setup.py
tuiqiao/MistakeCorrector.py
tuiqiao/N_gram.py
tuiqiao/PinyinCorrector.py
tuiqiao/TrieTree.py
tuiqiao/__init__.py
tuiqiao/main.py
tuiqiao/train.py
tuiqiao.egg-info/PKG-INFO
tuiqiao.egg-info/SOURCES.txt
tuiqiao.egg-info/dependency_links.txt
tuiqiao.egg-info/top_level.txt
tuiqiao/data/Confusion_SimilarPronunciation.pk
tuiqiao/data/Confusion_SimilarShape.pk
tuiqiao/data/Pronunciation.txt
tuiqiao/data/Shape.txt
tuiqiao/data/__init__.py
tuiqiao/data/dict.txt
tuiqiao/data/mistake.model
tuiqiao/data/pinyin2word.model
tuiqiao/data/pinyin_set.model
tuiqiao/data/small.pk
tuiqiao/data/stopword.txt
tuiqiao/data/trie.model
tuiqiao/utils/__init__.py
tuiqiao/utils/data.py