Metadata-Version: 1.0
Name: tuiqiao
Version: 0.6.0
Summary: a spelling correction tool for Chinese
Home-page: https://github.com/HDL951236874/tuiqiao
Author: Daolin Han
Author-email: 2862308357@qq.com
License: MIT Licence
Platform: UNKNOWN
